MANIFEST.in
setup.py
src/startproj/__init__.py
src/startproj/main.py
src/startproj/template.py
src/startproj/util.py
src/startproj.egg-info/PKG-INFO
src/startproj.egg-info/SOURCES.txt
src/startproj.egg-info/dependency_links.txt
src/startproj.egg-info/entry_points.txt
src/startproj.egg-info/requires.txt
src/startproj.egg-info/top_level.txt