Metadata-Version: 1.0
Name: startproj
Version: 0.1
Summary: Quickly creates a code directory from a template project
Home-page: https://github.com/nathforge/startproj
Author: Nathan Reynolds
Author-email: email@nreynolds.co.uk
License: UNKNOWN
Platform: UNKNOWN
